mktanalytics/__init__.py
mktanalytics/mktanalytics.py
mktanalytics-0.0.2.dist-info/LICENSE
mktanalytics-0.0.2.dist-info/METADATA
mktanalytics-0.0.2.dist-info/WHEEL
mktanalytics-0.0.2.dist-info/top_level.txt
mktanalytics-0.0.2.dist-info/RECORD
