Metadata-Version: 2.1
Name: mktanalytics
Version: 0.0.2
Summary: mktanalytics is a python package for analyzing markets.
Home-page: https://github.com/paytonong/mktanalytics
Author: Payton Ong
Author-email: payton.ong@gmail.com
License: MIT
Platform: UNKNOWN
Classifier: Development Status :: 3 - Alpha
Classifier: License :: OSI Approved :: MIT License
Classifier: Programming Language :: Python
Classifier: Programming Language :: Python :: 3.5
Classifier: Programming Language :: Python :: 3.6
Classifier: Programming Language :: Python :: 3.7
Classifier: Topic :: Software Development :: Libraries
Classifier: Topic :: Software Development :: Libraries :: Python Modules
Classifier: Intended Audience :: Developers
Requires-Python: >=3.5
Requires-Dist: numpy
Requires-Dist: pandas
